acia/__init__.py
acia/acia.py
acia/attribute.py
acia/base.py
acia/cli.py
acia/utils.py
acia/analysis/__init__.py
acia/segm/__init__.py
acia/segm/filter.py
acia/segm/formats.py
acia/segm/local.py
acia/segm/output.py
acia/segm/utils.py
acia/segm/omero/__init__.py
acia/segm/omero/shapeUtils.py
acia/segm/omero/storer.py
acia/segm/omero/utils.py
acia/segm/processor/__init__.py
acia/segm/processor/cellpose.py
acia/segm/processor/cellpose_sam.py
acia/segm/processor/cpn.py
acia/segm/processor/offline.py
acia/segm/processor/omnipose.py
acia/segm/processor/online.py
acia/segm/processor/predict.py
acia/segm/processor/yolo.py
acia/tracking/__init__.py
acia/tracking/analysis.py
acia/tracking/formats.py
acia/tracking/output.py
acia/tracking/utils.py
acia/tracking/processor/__init__.py
acia/tracking/processor/laptrack.py
acia/tracking/processor/pyuat.py
acia/tracking/processor/trackastra.py
acia/tracking/processor/ultrack.py
acia/tracking/processor/utils.py
acia/viz/__init__.py
acia/viz/utils.py
acia-0.3.1.dist-info/licenses/AUTHORS.rst
acia-0.3.1.dist-info/licenses/LICENSE
acia-0.3.1.dist-info/METADATA
acia-0.3.1.dist-info/WHEEL
acia-0.3.1.dist-info/top_level.txt
acia-0.3.1.dist-info/RECORD
